{
  "main": {
    "id": "5324373015726ba8",
    "type": "split",
    "children": [
      {
        "id": "4509724f8bf84da7",
        "type": "tabs",
        "children": [
          {
            "id": "e7a7b303c61786dc",
            "type": "leaf",
            "pinned": true,
            "state": {
              "type": "markdown",
              "state": {
                "file": "00_Dashboard/Java_Dashboard.md.md",
                "mode": "source",
                "source": false
              },
              "pinned": true,
              "icon": "lucide-file",
              "title": "Java_Dashboard.md"
            }
          }
        ]
      }
    ],
    "direction": "vertical"
  },
  "left": {
    "id": "0061a4b7c24a281e",
    "type": "split",
    "children": [
      {
        "id": "c315b489af02b745",
        "type": "tabs",
        "children": [
          {
            "id": "39954a23d541ef61",
            "type": "leaf",
            "state": {
              "type": "file-explorer",
              "state": {
                "sortOrder": "alphabetical",
                "autoReveal": false
              },
              "icon": "lucide-folder-closed",
              "title": "Файловый менеджер"
            }
          },
          {
            "id": "244a0905f108e4d7",
            "type": "leaf",
            "state": {
              "type": "search",
              "state": {
                "query": "",
                "matchingCase": false,
                "explainSearch": false,
                "collapseAll": false,
                "extraContext": false,
                "sortOrder": "alphabetical"
              },
              "icon": "lucide-search",
              "title": "Поиск"
            }
          },
          {
            "id": "3ba3c18c8ca7421b",
            "type": "leaf",
            "state": {
              "type": "bookmarks",
              "state": {},
              "icon": "lucide-bookmark",
              "title": "Закладки"
            }
          }
        ]
      }
    ],
    "direction": "horizontal",
    "width": 300
  },
  "right": {
    "id": "044a28265bde634a",
    "type": "split",
    "children": [
      {
        "id": "a38d4dfc7af10f3f",
        "type": "tabs",
        "children": [
          {
            "id": "cdcc9a5cb18a1c57",
            "type": "leaf",
            "state": {
              "type": "backlink",
              "state": {
                "file": "Dateienformat/HTTP.md",
                "collapseAll": false,
                "extraContext": false,
                "sortOrder": "alphabetical",
                "showSearch": false,
                "searchQuery": "",
                "backlinkCollapsed": false,
                "unlinkedCollapsed": true
              },
              "icon": "links-coming-in",
              "title": "Обратные ссылки для HTTP"
            }
          },
          {
            "id": "6736ca0be2176b55",
            "type": "leaf",
            "state": {
              "type": "outgoing-link",
              "state": {
                "file": "Dateienformat/HTTP.md",
                "linksCollapsed": false,
                "unlinkedCollapsed": true
              },
              "icon": "links-going-out",
              "title": "Исходящие ссылки из HTTP"
            }
          },
          {
            "id": "ceec950f4e3ee2bc",
            "type": "leaf",
            "state": {
              "type": "tag",
              "state": {
                "sortOrder": "frequency",
                "useHierarchy": true,
                "showSearch": false,
                "searchQuery": ""
              },
              "icon": "lucide-tags",
              "title": "Теги"
            }
          },
          {
            "id": "ede7512514f48b4a",
            "type": "leaf",
            "state": {
              "type": "all-properties",
              "state": {
                "sortOrder": "frequency",
                "showSearch": false,
                "searchQuery": ""
              },
              "icon": "lucide-archive",
              "title": "Все свойства"
            }
          },
          {
            "id": "fbacb5c1f1b1be40",
            "type": "leaf",
            "state": {
              "type": "outline",
              "state": {
                "file": "Dateienformat/HTTP.md",
                "followCursor": false,
                "showSearch": false,
                "searchQuery": ""
              },
              "icon": "lucide-list",
              "title": "Структура HTTP"
            }
          }
        ],
        "currentTab": 2
      }
    ],
    "direction": "horizontal",
    "width": 300,
    "collapsed": true
  },
  "left-ribbon": {
    "hiddenItems": {
      "switcher:Меню быстрого перехода": false,
      "graph:Граф": false,
      "canvas:Создать новый холст": false,
      "daily-notes:Сегодняшняя заметка": false,
      "templates:Вставить шаблон": false,
      "command-palette:Открыть палитру команд": false,
      "bases:Создать новую базу": false,
      "obsidian-excalidraw-plugin:Создать новый чертеж": false,
      "obsidian-git:Open Git source control": false,
      "templater-obsidian:Templater": false,
      "omnisearch:Omnisearch": false,
      "homepage:Open homepage": false
    }
  },
  "active": "e7a7b303c61786dc",
  "lastOpenFiles": [
    "00_Dashboard/Java_Dashboard.md.md",
    "00_Dashboard/Java_Roadmap.md.md",
    "02_OOP/OOP.md.md",
    "Template 2/java_bug.md.md",
    "Template 1/Java_concept.md.md",
    "java_snippet.md.md",
    "Template 3",
    "Template 2",
    "Template 1",
    "Dateienformat/HTTP.md",
    "99_Archive",
    "19_Architecture_Diagrams",
    "18_Projects",
    "17_Interview_Questions",
    "16_Code_Snippets",
    "15_Performance",
    "14_Debugging_Bugs",
    "Без названия.canvas",
    "Dateienformat/JSON.md",
    "JSON.md",
    "Dateienformat/XML.md",
    "HTTP.md",
    "XML.md",
    "2026-03-05.md",
    "Добро пожаловать.md"
  ]
}